bia_bob/__init__.py
bia_bob/_accelerate.py
bia_bob/_bug_fixing.py
bia_bob/_document.py
bia_bob/_machinery.py
bia_bob/_notebook_generation.py
bia_bob/_terminal.py
bia_bob/_utilities.py
bia_bob/_tests/__init__.py
bia_bob/endpoints/__init__.py
bia_bob/endpoints/_anthropic.py
bia_bob/endpoints/_azure.py
bia_bob/endpoints/_googlevertex.py
bia_bob/endpoints/_mistral.py
bia_bob/endpoints/_openai.py
bia_bob/suggestions/__init__.py
bia_bob/suggestions/_aicsimageio.py
bia_bob/suggestions/_cellpose.py
bia_bob/suggestions/_czifile.py
bia_bob/suggestions/_ipywidgets.py
bia_bob/suggestions/_pandas.py
bia_bob/suggestions/_scikit_image.py
bia_bob-0.34.3.dist-info/licenses/LICENSE
bia_bob-0.34.3.dist-info/METADATA
bia_bob-0.34.3.dist-info/WHEEL
bia_bob-0.34.3.dist-info/entry_points.txt
bia_bob-0.34.3.dist-info/top_level.txt
bia_bob-0.34.3.dist-info/RECORD
