Metadata-Version: 2.4
Name: bia-bob
Version: 0.34.3
Summary: A Jupyter-based assistant for image data analysis tasks
Home-page: https://github.com/haesleinhuepf/bia-bob
Author: Robert Haase, Christian Tischer
Author-email: robert.haase@uni-leipzig.de
License: BSD-3-Clause
Project-URL: Bug Tracker, https://github.com/haesleinhuepf/bia-bob/issues
Project-URL: Documentation, https://github.com/haesleinhuepf/bia-bob#README.md
Project-URL: Source Code, https://github.com/haesleinhuepf/bia-bob
Project-URL: User Support, https://github.com/haesleinhuepf/bia-bob/issues
Classifier: Development Status :: 2 - Pre-Alpha
Classifier: Intended Audience :: Developers
Classifier: License :: OSI Approved :: BSD License
Classifier: Operating System :: OS Independent
Classifier: Programming Language :: Python
Classifier: Programming Language :: Python :: 3
Classifier: Programming Language :: Python :: 3 :: Only
Classifier: Programming Language :: Python :: 3.8
Classifier: Programming Language :: Python :: 3.9
Classifier: Programming Language :: Python :: 3.10
Classifier: Programming Language :: Python :: 3.11
Classifier: Programming Language :: Python :: 3.12
Classifier: Topic :: Scientific/Engineering :: Image Processing
Requires-Python: >=3.8
License-File: LICENSE
Requires-Dist: numpy
Requires-Dist: ipython
Requires-Dist: jupyter_client
Requires-Dist: metakernel
Requires-Dist: Pillow
Requires-Dist: openai>=1.82.1
Requires-Dist: anthropic>=0.30.1
Requires-Dist: ipynbname>=2024.1.0.0
Requires-Dist: azure-ai-inference>=1.0.0b4
Requires-Dist: mistralai>=1.0.0
Requires-Dist: siphash24
Provides-Extra: testing
Requires-Dist: tox; extra == "testing"
Requires-Dist: pytest; extra == "testing"
Requires-Dist: pytest-cov; extra == "testing"
Dynamic: license-file
